_version.py
zilla_package/app.py
zilla_package/zilla.py
zilla_package-0.1.1.dist-info/LICENSE
zilla_package-0.1.1.dist-info/METADATA
zilla_package-0.1.1.dist-info/WHEEL
zilla_package-0.1.1.dist-info/entry_points.txt
zilla_package-0.1.1.dist-info/top_level.txt
zilla_package-0.1.1.dist-info/RECORD
