Metadata-Version: 2.2
Name: zilla-package
Version: 0.1.1
Summary: A simple package
Author-email: Fabio Bove <fabio.bove.dr@gmail.com>
License:                     GNU GENERAL PUBLIC LICENSE
Project-URL: Homepage, https://github.com/fabiobove-dr/zilla-package
Project-URL: Issues, https://github.com/fabiobove-dr/zilla-package/issues
Keywords: python-package
License-File: LICENSE
Provides-Extra: test
Requires-Dist: pytest==7.3.2; extra == "test"
Requires-Dist: pytest-cov==5.0.0; extra == "test"
Provides-Extra: cuda
Requires-Dist: torch[cuda]==2.3.1; extra == "cuda"
Provides-Extra: cpu
Requires-Dist: torch==2.3.1; extra == "cpu"
